{
  "version": 2,
  "extractor": "papercropper",
  "tables": [
    {
      "url": "assets/tables/openreview/openreview-icml-2025-avvxx0erkt/table-001.webp",
      "caption": "",
      "page": 0,
      "index": 1,
      "width": 835,
      "height": 435,
      "label": "Table"
    },
    {
      "url": "assets/tables/openreview/openreview-icml-2025-avvxx0erkt/table-002.webp",
      "caption": "",
      "page": 0,
      "index": 2,
      "width": 1068,
      "height": 421,
      "label": "Table"
    },
    {
      "url": "assets/tables/openreview/openreview-icml-2025-avvxx0erkt/table-003.webp",
      "caption": "",
      "page": 0,
      "index": 3,
      "width": 1638,
      "height": 239,
      "label": "Table"
    }
  ]
}