{
  "version": 2,
  "extractor": "papercropper",
  "figures": [
    {
      "url": "assets/figures/arxiv/2606.13677v1/fig-001.webp",
      "caption": "",
      "page": 0,
      "index": 1,
      "width": 1445,
      "height": 768,
      "label": "Figure"
    },
    {
      "url": "assets/figures/arxiv/2606.13677v1/fig-002.webp",
      "caption": "",
      "page": 0,
      "index": 2,
      "width": 1425,
      "height": 368,
      "label": "Figure"
    },
    {
      "url": "assets/figures/arxiv/2606.13677v1/fig-003.webp",
      "caption": "",
      "page": 0,
      "index": 3,
      "width": 1447,
      "height": 667,
      "label": "Figure"
    },
    {
      "url": "assets/figures/arxiv/2606.13677v1/fig-004.webp",
      "caption": "",
      "page": 0,
      "index": 4,
      "width": 1448,
      "height": 316,
      "label": "Figure"
    },
    {
      "url": "assets/figures/arxiv/2606.13677v1/fig-005.webp",
      "caption": "",
      "page": 0,
      "index": 5,
      "width": 1453,
      "height": 404,
      "label": "Figure"
    },
    {
      "url": "assets/figures/arxiv/2606.13677v1/fig-006.webp",
      "caption": "",
      "page": 0,
      "index": 6,
      "width": 1434,
      "height": 468,
      "label": "Figure"
    },
    {
      "url": "assets/figures/arxiv/2606.13677v1/fig-007.webp",
      "caption": "",
      "page": 0,
      "index": 7,
      "width": 1437,
      "height": 303,
      "label": "Figure"
    },
    {
      "url": "assets/figures/arxiv/2606.13677v1/fig-008.webp",
      "caption": "",
      "page": 0,
      "index": 8,
      "width": 1448,
      "height": 291,
      "label": "Figure"
    },
    {
      "url": "assets/figures/arxiv/2606.13677v1/fig-009.webp",
      "caption": "",
      "page": 0,
      "index": 9,
      "width": 1445,
      "height": 670,
      "label": "Figure"
    }
  ]
}