{
  "version": 2,
  "extractor": "papercropper",
  "figures": [
    {
      "url": "assets/figures/openreview/openreview-icml-2025-n1cqqk4hhc/fig-001.webp",
      "caption": "",
      "page": 0,
      "index": 1,
      "width": 858,
      "height": 607,
      "label": "Figure"
    },
    {
      "url": "assets/figures/openreview/openreview-icml-2025-n1cqqk4hhc/fig-002.webp",
      "caption": "",
      "page": 0,
      "index": 2,
      "width": 1434,
      "height": 855,
      "label": "Figure"
    },
    {
      "url": "assets/figures/openreview/openreview-icml-2025-n1cqqk4hhc/fig-003.webp",
      "caption": "",
      "page": 0,
      "index": 3,
      "width": 853,
      "height": 603,
      "label": "Figure"
    },
    {
      "url": "assets/figures/openreview/openreview-icml-2025-n1cqqk4hhc/fig-004.webp",
      "caption": "",
      "page": 0,
      "index": 4,
      "width": 853,
      "height": 585,
      "label": "Figure"
    },
    {
      "url": "assets/figures/openreview/openreview-icml-2025-n1cqqk4hhc/fig-005.webp",
      "caption": "",
      "page": 0,
      "index": 5,
      "width": 1579,
      "height": 957,
      "label": "Figure"
    },
    {
      "url": "assets/figures/openreview/openreview-icml-2025-n1cqqk4hhc/fig-006.webp",
      "caption": "",
      "page": 0,
      "index": 6,
      "width": 1768,
      "height": 266,
      "label": "Figure"
    },
    {
      "url": "assets/figures/openreview/openreview-icml-2025-n1cqqk4hhc/fig-007.webp",
      "caption": "",
      "page": 0,
      "index": 7,
      "width": 1765,
      "height": 1170,
      "label": "Figure"
    },
    {
      "url": "assets/figures/openreview/openreview-icml-2025-n1cqqk4hhc/fig-008.webp",
      "caption": "",
      "page": 0,
      "index": 8,
      "width": 1600,
      "height": 1338,
      "label": "Figure"
    },
    {
      "url": "assets/figures/openreview/openreview-icml-2025-n1cqqk4hhc/fig-009.webp",
      "caption": "",
      "page": 0,
      "index": 9,
      "width": 1741,
      "height": 2155,
      "label": "Figure"
    }
  ]
}