{
  "version": 2,
  "extractor": "papercropper",
  "figures": [
    {
      "url": "assets/figures/arxiv/2606.08533v1/fig-001.webp",
      "caption": "",
      "page": 0,
      "index": 1,
      "width": 1475,
      "height": 849,
      "label": "Figure"
    },
    {
      "url": "assets/figures/arxiv/2606.08533v1/fig-002.webp",
      "caption": "",
      "page": 0,
      "index": 2,
      "width": 1423,
      "height": 446,
      "label": "Figure"
    },
    {
      "url": "assets/figures/arxiv/2606.08533v1/fig-003.webp",
      "caption": "",
      "page": 0,
      "index": 3,
      "width": 649,
      "height": 382,
      "label": "Figure"
    },
    {
      "url": "assets/figures/arxiv/2606.08533v1/fig-004.webp",
      "caption": "",
      "page": 0,
      "index": 4,
      "width": 1685,
      "height": 443,
      "label": "Figure"
    },
    {
      "url": "assets/figures/arxiv/2606.08533v1/fig-005.webp",
      "caption": "",
      "page": 0,
      "index": 5,
      "width": 918,
      "height": 393,
      "label": "Figure"
    },
    {
      "url": "assets/figures/arxiv/2606.08533v1/fig-006.webp",
      "caption": "",
      "page": 0,
      "index": 6,
      "width": 1624,
      "height": 475,
      "label": "Figure"
    },
    {
      "url": "assets/figures/arxiv/2606.08533v1/fig-007.webp",
      "caption": "",
      "page": 0,
      "index": 7,
      "width": 1484,
      "height": 429,
      "label": "Figure"
    },
    {
      "url": "assets/figures/arxiv/2606.08533v1/fig-008.webp",
      "caption": "",
      "page": 0,
      "index": 8,
      "width": 698,
      "height": 552,
      "label": "Figure"
    },
    {
      "url": "assets/figures/arxiv/2606.08533v1/fig-009.webp",
      "caption": "",
      "page": 0,
      "index": 9,
      "width": 1524,
      "height": 689,
      "label": "Figure"
    },
    {
      "url": "assets/figures/arxiv/2606.08533v1/fig-010.webp",
      "caption": "",
      "page": 0,
      "index": 10,
      "width": 1675,
      "height": 387,
      "label": "Figure"
    },
    {
      "url": "assets/figures/arxiv/2606.08533v1/fig-011.webp",
      "caption": "",
      "page": 0,
      "index": 11,
      "width": 631,
      "height": 585,
      "label": "Figure"
    },
    {
      "url": "assets/figures/arxiv/2606.08533v1/fig-012.webp",
      "caption": "",
      "page": 0,
      "index": 12,
      "width": 1700,
      "height": 351,
      "label": "Figure"
    }
  ]
}